chronos/__init__.py
chronos/base.py
chronos/chronos.py
chronos/chronos_bolt.py
chronos/utils.py
timecopilot_chronos_forecasting-0.1.0.dist-info/METADATA
timecopilot_chronos_forecasting-0.1.0.dist-info/WHEEL
timecopilot_chronos_forecasting-0.1.0.dist-info/licenses/LICENSE
timecopilot_chronos_forecasting-0.1.0.dist-info/licenses/NOTICE
timecopilot_chronos_forecasting-0.1.0.dist-info/RECORD
