Metadata-Version: 2.4
Name: timecopilot-chronos-forecasting
Version: 0.1.0
Summary: Chronos: Pretrained models for time series forecasting
Project-URL: Homepage, https://github.com/amazon-science/chronos-forecasting
Project-URL: Issues, https://github.com/amazon-science/chronos-forecasting/issues
Project-URL: Paper, https://arxiv.org/abs/2403.07815
License: 
License-File: LICENSE
License-File: NOTICE
Classifier: License :: OSI Approved :: Apache Software License
Classifier: Operating System :: OS Independent
Classifier: Programming Language :: Python :: 3
Classifier: Topic :: Scientific/Engineering :: Artificial Intelligence
Requires-Python: >=3.9
Requires-Dist: accelerate<2,>=0.32
Requires-Dist: torch<3,>=2.0
Requires-Dist: transformers<5,>=4.40.1
Provides-Extra: evaluation
Requires-Dist: datasets<4,>=2.18; extra == 'evaluation'
Requires-Dist: gluonts[pro]~=0.15; extra == 'evaluation'
Requires-Dist: numpy<3,>=1.21; extra == 'evaluation'
Requires-Dist: typer; extra == 'evaluation'
Provides-Extra: test
Requires-Dist: numpy<3,>=1.21; extra == 'test'
Requires-Dist: pytest~=8.0; extra == 'test'
Provides-Extra: training
Requires-Dist: datasets<4,>=2.18; extra == 'training'
Requires-Dist: gluonts[pro]~=0.15; extra == 'training'
Requires-Dist: joblib; extra == 'training'
Requires-Dist: numpy<3,>=1.21; extra == 'training'
Requires-Dist: scikit-learn; extra == 'training'
Requires-Dist: tensorboard; extra == 'training'
Requires-Dist: typer; extra == 'training'
Requires-Dist: typer-config; extra == 'training'
Provides-Extra: typecheck
Requires-Dist: mypy~=1.9; extra == 'typecheck'
